google_sheets_sdk/__init__.py
google_sheets_sdk/client/__init__.py
google_sheets_sdk/common/__init__.py
google_sheets_sdk/core/__init__.py
google_sheets_sdk/core/models.py
google_sheets_sdk/core/settings.py
google_sheets_sdk-0.3.2.dist-info/LICENSE
google_sheets_sdk-0.3.2.dist-info/METADATA
google_sheets_sdk-0.3.2.dist-info/WHEEL
google_sheets_sdk-0.3.2.dist-info/RECORD
