Metadata-Version: 2.3
Name: google-sheets-sdk
Version: 0.3.2
Summary: 
License: MIT
Author: Marco Carmona
Author-email: marcocarmonadev@outlook.com
Requires-Python: >=3.10,<4.0
Classifier: License :: OSI Approved :: MIT License
Classifier: Programming Language :: Python :: 3
Classifier: Programming Language :: Python :: 3.10
Classifier: Programming Language :: Python :: 3.11
Classifier: Programming Language :: Python :: 3.12
Classifier: Programming Language :: Python :: 3.13
Requires-Dist: httpx (>=0.27.0,<0.28.0)
Requires-Dist: pydantic-settings (>=2.2.1,<3.0.0)
Requires-Dist: pydantic[email] (>=2.6.4,<3.0.0)
Requires-Dist: python-jose (>=3.3.0,<4.0.0)
